{
    "_id": "62d2f02e751567007abb1864",
    "game_ref": {
        "uniq_name": null
    },
    "url_name": "grineer_warden",
    "icon": "npc/images/grineer_warden.0e22a57f238b772e6b1fd68e46de6c93.png",
    "thumb": "npc/images/thumbs/grineer_warden.0e22a57f238b772e6b1fd68e46de6c93.128x128.png",
    "i18n": {
        "en": {
            "name": "Grineer Warden"
        },
        "ru": {
            "name": "Grineer Warden"
        },
        "ko": {
            "name": "Grineer Warden"
        },
        "de": {
            "name": "Grineer Warden"
        },
        "fr": {
            "name": "Grineer Warden"
        },
        "pt": {
            "name": "Grineer Warden"
        },
        "zh-hans": {
            "name": "Grineer典狱长"
        },
        "zh-hant": {
            "name": "Grineer典獄長"
        },
        "es": {
            "name": "Grineer Warden"
        },
        "it": {
            "name": "Grineer Warden"
        },
        "pl": {
            "name": "Grineer Warden"
        },
        "uk": {
            "name": "Grineer Warden"
        }
    }
}