{
    "_id": "62d2f014751567007abb1790",
    "game_ref": {
        "uniq_name": null
    },
    "url_name": "hemocyte",
    "i18n": {
        "en": {
            "name": "Hemocyte",
            "icon": "npc/images/hemocyte.ee3b96d2ef3b991e0ee652f35b8b175a.png",
            "thumb": "npc/images/thumbs/hemocyte.ee3b96d2ef3b991e0ee652f35b8b175a.128x128.png"
        },
        "ru": {
            "name": "Hemocyte",
            "icon": "npc/images/hemocyte.ee3b96d2ef3b991e0ee652f35b8b175a.png",
            "thumb": "npc/images/thumbs/hemocyte.ee3b96d2ef3b991e0ee652f35b8b175a.128x128.png"
        },
        "ko": {
            "name": "Hemocyte",
            "icon": "npc/images/hemocyte.ee3b96d2ef3b991e0ee652f35b8b175a.png",
            "thumb": "npc/images/thumbs/hemocyte.ee3b96d2ef3b991e0ee652f35b8b175a.128x128.png"
        },
        "de": {
            "name": "Hemocyte",
            "icon": "npc/images/hemocyte.ee3b96d2ef3b991e0ee652f35b8b175a.png",
            "thumb": "npc/images/thumbs/hemocyte.ee3b96d2ef3b991e0ee652f35b8b175a.128x128.png"
        },
        "fr": {
            "name": "Hemocyte",
            "icon": "npc/images/hemocyte.ee3b96d2ef3b991e0ee652f35b8b175a.png",
            "thumb": "npc/images/thumbs/hemocyte.ee3b96d2ef3b991e0ee652f35b8b175a.128x128.png"
        },
        "pt": {
            "name": "Hemocyte",
            "icon": "npc/images/hemocyte.ee3b96d2ef3b991e0ee652f35b8b175a.png",
            "thumb": "npc/images/thumbs/hemocyte.ee3b96d2ef3b991e0ee652f35b8b175a.128x128.png"
        },
        "zh-hans": {
            "name": "免疫血胞体",
            "icon": "npc/images/hemocyte.ee3b96d2ef3b991e0ee652f35b8b175a.png",
            "thumb": "npc/images/thumbs/hemocyte.ee3b96d2ef3b991e0ee652f35b8b175a.128x128.png"
        },
        "zh-hant": {
            "name": "免疫血胞體",
            "icon": "npc/images/hemocyte.ee3b96d2ef3b991e0ee652f35b8b175a.png",
            "thumb": "npc/images/thumbs/hemocyte.ee3b96d2ef3b991e0ee652f35b8b175a.128x128.png"
        },
        "es": {
            "name": "Hemocyte",
            "icon": "npc/images/hemocyte.ee3b96d2ef3b991e0ee652f35b8b175a.png",
            "thumb": "npc/images/thumbs/hemocyte.ee3b96d2ef3b991e0ee652f35b8b175a.128x128.png"
        },
        "it": {
            "name": "Hemocyte",
            "icon": "npc/images/hemocyte.ee3b96d2ef3b991e0ee652f35b8b175a.png",
            "thumb": "npc/images/thumbs/hemocyte.ee3b96d2ef3b991e0ee652f35b8b175a.128x128.png"
        },
        "pl": {
            "name": "Hemocyte",
            "icon": "npc/images/hemocyte.ee3b96d2ef3b991e0ee652f35b8b175a.png",
            "thumb": "npc/images/thumbs/hemocyte.ee3b96d2ef3b991e0ee652f35b8b175a.128x128.png"
        },
        "uk": {
            "name": "Гемоцит",
            "icon": "npc/images/hemocyte.ee3b96d2ef3b991e0ee652f35b8b175a.png",
            "thumb": "npc/images/thumbs/hemocyte.ee3b96d2ef3b991e0ee652f35b8b175a.128x128.png"
        }
    }
}