{
    "_id": "62d2f02d751567007abb185c",
    "game_ref": {
        "uniq_name": null
    },
    "url_name": "kuva_bombard",
    "icon": "npc/images/kuva_bombard.82b435f669f6218dba5cf5958341f5ad.png",
    "thumb": "npc/images/thumbs/kuva_bombard.82b435f669f6218dba5cf5958341f5ad.128x128.png",
    "en": {
        "name": "Kuva Bombard"
    },
    "ru": {
        "name": "Kuva Bombard"
    },
    "ko": {
        "name": "Kuva Bombard"
    },
    "de": {
        "name": "Kuva Bombard"
    },
    "fr": {
        "name": "Kuva Bombard"
    },
    "pt": {
        "name": "Kuva Bombard"
    },
    "zh-hans": {
        "name": "赤毒轰击者"
    },
    "zh-hant": {
        "name": "赤毒轟擊者"
    },
    "es": {
        "name": "Kuva Bombard"
    },
    "it": {
        "name": "Kuva Bombard"
    },
    "pl": {
        "name": "Kuva Bombard"
    }
}