{
    "_id": "62d2effe751567007abb16e2",
    "game_ref": {
        "uniq_name": null
    },
    "url_name": "orm_nullifier_crewman",
    "icon": "npc/images/orm_nullifier_crewman.fc21aff53b32a58bf2c2e994d2c225fe.png",
    "thumb": "npc/images/thumbs/orm_nullifier_crewman.fc21aff53b32a58bf2c2e994d2c225fe.128x128.png",
    "i18n": {
        "en": {
            "name": "Orm Nullifier Crewman"
        },
        "ru": {
            "name": "Orm Nullifier Crewman"
        },
        "ko": {
            "name": "Orm Nullifier Crewman"
        },
        "de": {
            "name": "Orm Nullifier Crewman"
        },
        "fr": {
            "name": "Orm Nullifier Crewman"
        },
        "pt": {
            "name": "Orm Nullifier Crewman"
        },
        "zh-hans": {
            "name": "奥穆虚能船员"
        },
        "zh-hant": {
            "name": "奧姆虛能船員"
        },
        "es": {
            "name": "Orm Nullifier Crewman"
        },
        "it": {
            "name": "Orm Nullifier Crewman"
        },
        "pl": {
            "name": "Orm Nullifier Crewman"
        },
        "uk": {
            "name": "Рядовий-нуліфікатор «Орма»"
        }
    }
}