{
    "_id": "62d2f00b751567007abb174c",
    "game_ref": {
        "uniq_name": null
    },
    "url_name": "taro_crewman",
    "icon": "npc/images/taro_crewman.8470c0323ac6d90370ade1b80debda86.png",
    "thumb": "npc/images/thumbs/taro_crewman.8470c0323ac6d90370ade1b80debda86.128x128.png",
    "en": {
        "name": "Taro Crewman"
    },
    "ru": {
        "name": "Taro Crewman"
    },
    "ko": {
        "name": "Taro Crewman"
    },
    "de": {
        "name": "Taro Crewman"
    },
    "fr": {
        "name": "Taro Crewman"
    },
    "pt": {
        "name": "Taro Crewman"
    },
    "zh-hans": {
        "name": "Taro Crewman"
    },
    "zh-hant": {
        "name": "Taro Crewman"
    },
    "es": {
        "name": "Taro Crewman"
    },
    "it": {
        "name": "Taro Crewman"
    },
    "pl": {
        "name": "Taro Crewman"
    }
}