{
    "_id": "62d2f02e751567007abb1861",
    "game_ref": {
        "uniq_name": null
    },
    "url_name": "temporal_dreg",
    "icon": "npc/images/temporal_dreg.f7973c5a4d96bad436eac31954349669.png",
    "thumb": "npc/images/thumbs/temporal_dreg.f7973c5a4d96bad436eac31954349669.128x128.png",
    "i18n": {
        "en": {
            "name": "Temporal Dreg"
        },
        "ru": {
            "name": "Temporal Dreg"
        },
        "ko": {
            "name": "Temporal Dreg"
        },
        "de": {
            "name": "Temporal Dreg"
        },
        "fr": {
            "name": "Temporal Dreg"
        },
        "pt": {
            "name": "Temporal Dreg"
        },
        "zh-hans": {
            "name": "滞缓无人机"
        },
        "zh-hant": {
            "name": "滯緩無人機"
        },
        "es": {
            "name": "Temporal Dreg"
        },
        "it": {
            "name": "Temporal Dreg"
        },
        "pl": {
            "name": "Temporal Dreg"
        },
        "uk": {
            "name": "Дреґ-сповільнювач"
        }
    }
}