{
    "_id": "5a0475086c4655012038ddc0",
    "tags": [
        "arcane enhancements",
        "zaw"
    ],
    "icon": "icons/en/Exodia_Valor.6944e42105fc09e60c8a843acedfd7cf.png",
    "thumb": "icons/en/thumbs/Exodia_Valor.6944e42105fc09e60c8a843acedfd7cf.128x128.png",
    "icon_format": "land",
    "url_name": "exodia_valor",
    "tradable": true,
    "en": {
        "item_name": "Exodia Valor",
        "description": "<p>Exodia Valor is an Arcane Enhancement for Zaws that grants a chance to increase channeling damage for a few seconds on Critical Hits.</p>",
        "wiki_link": "http://warframe.wikia.com/wiki/Exodia_Valor",
        "drop": []
    },
    "ru": {
        "item_name": "Доблесть Эксодии",
        "description": "<p>Доблесть Эксодии - мистификатор для Зо, который с некоторым шансом временно увеличивает урон режима концентрации при срабатывании критического урона.</p>",
        "wiki_link": "http://ru.warframe.wikia.com/wiki/%D0%94%D0%BE%D0%B1%D0%BB%D0%B5%D1%81%D1%82%D1%8C_%D0%AD%D0%BA%D1%81%D0%BE%D0%B4%D0%B8%D0%B8",
        "drop": []
    },
    "ko": {
        "item_name": "엑소디아 발러",
        "description": "<p>Exodia Valor is an Arcane Enhancement for Zaws that grants a chance to increase channeling damage for a few seconds on Critical Hits.</p>",
        "wiki_link": "http://warframe.wikia.com/wiki/Exodia_Valor",
        "drop": []
    },
    "mod_max_rank": 3,
    "trading_tax": 0
}