{
    "_id": "5dbe9b0d7ea27b0ffe3ca275",
    "tags": [
        "mod",
        "warframe",
        "uncommon",
        "parazon"
    ],
    "icon": "icons/en/auto_breach.84fc19699e6af7b4d32529aff017634c.png",
    "thumb": "icons/en/thumbs/auto_breach.84fc19699e6af7b4d32529aff017634c.128x128.png",
    "icon_format": "port",
    "url_name": "auto_breach",
    "tradable": true,
    "en": {
        "item_name": "Auto Breach",
        "description": "<p>Auto Breach is a Parazon mod that gives a chance of auto completing a Hacking console.</p>",
        "wiki_link": "https://warframe.fandom.com/wiki/Auto_Breach",
        "drop": []
    },
    "ru": {
        "item_name": "Автоматический Взлом",
        "description": "<p>Автоматический Взлом — необычный модификатор для Паразона, который с вероятностью 30% автоматически взломает консоль.</p>",
        "wiki_link": "https://warframe.fandom.com/ru/wiki/%D0%90%D0%B2%D1%82%D0%BE%D0%BC%D0%B0%D1%82%D0%B8%D1%87%D0%B5%D1%81%D0%BA%D0%B8%D0%B9_%D0%92%D0%B7%D0%BB%D0%BE%D0%BC",
        "icon": "icons/ru/auto_breach.c5d48eefa94597c8e87e40dea9e06df6.png",
        "thumb": "icons/ru/thumbs/auto_breach.c5d48eefa94597c8e87e40dea9e06df6.128x128.png",
        "drop": []
    },
    "ko": {
        "item_name": "Auto Breach",
        "description": "<p>Auto Breach is a Parazon mod that gives a chance of auto completing a Hacking console.</p>",
        "wiki_link": "https://warframe.fandom.com/wiki/Auto_Breach",
        "drop": []
    },
    "rarity": "uncommon",
    "trading_tax": 4000
}