{
    "_id": "5e9854b93d9f64004f9136bd",
    "url_name": "vengeful_shockwave",
    "icon": "icons/en/vengeful_shockwave.6020e14eb5e9516d4bc6ccf5023c864c.png",
    "thumb": "icons/en/thumbs/vengeful_shockwave.6020e14eb5e9516d4bc6ccf5023c864c.128x128.png",
    "icon_format": "port",
    "animation": "animations/vengeful_shockwave.971437bf48dec307ed268285b8798228.gif",
    "animation_format": "land",
    "element": "impact",
    "en": {
        "item_name": "Vengeful Shockwave",
        "wiki_link": "https://warframe.fandom.com/wiki/Kuva_Lich#Ephemera"
    },
    "ru": {
        "item_name": "Vengeful Shockwave",
        "wiki_link": "https://warframe.fandom.com/wiki/Kuva_Lich#Ephemera"
    },
    "ko": {
        "item_name": "Vengeful Shockwave",
        "wiki_link": "https://warframe.fandom.com/wiki/Kuva_Lich#Ephemera"
    }
}