{
    "_id": "5788fad54fff472f131a1360",
    "tags": [
        "mod",
        "kavat",
        "rare"
    ],
    "icon": "icons/en/Mischief.ea4ad1cb83cc9c58f7a51df554177b12.png",
    "thumb": "icons/en/thumbs/Mischief.ea4ad1cb83cc9c58f7a51df554177b12.128x128.png",
    "icon_format": "port",
    "url_name": "mischief",
    "tradable": true,
    "en": {
        "item_name": "Mischief",
        "description": "<p>Allows Smeeta Kavat to become invisible while a decoy kavat draws fire by running toward the enemy.</p>",
        "wiki_link": "http://warframe.wikia.com/wiki/Mischief",
        "drop": [
            {
                "name": "Feral Kavat",
                "link": null
            }
        ]
    },
    "ru": {
        "item_name": "Озорство",
        "description": "<p>Озорство — мод-заповедь для кавата Смита, позволяющий ему становиться невидимым и создавать приманку, отвлекающую противников.</p>",
        "wiki_link": "http://ru.warframe.wikia.com/wiki/%D0%9E%D0%B7%D0%BE%D1%80%D1%81%D1%82%D0%B2%D0%BE",
        "icon": "icons/ru/Mischief.1a4faef62888a8ac53ca586f0dc36af2.png",
        "thumb": "icons/ru/thumbs/Mischief.1a4faef62888a8ac53ca586f0dc36af2.128x128.png",
        "drop": [
            {
                "name": "Feral Kavat",
                "link": null
            }
        ]
    },
    "rarity": "rare",
    "mod_max_rank": 3,
    "trading_tax": 8000
}