{
    "_id": "5bc1ab93b919f200c18c10f0",
    "tags": [
        "mod",
        "warframe"
    ],
    "icon": "icons/en/Sharpshooter.82008706e945ec2bf7c88a0587ae404d.png",
    "thumb": "icons/en/thumbs/Sharpshooter.82008706e945ec2bf7c88a0587ae404d.128x128.png",
    "icon_format": "port",
    "url_name": "sharpshooter",
    "tradable": true,
    "en": {
        "item_name": "Sharpshooter",
        "description": "Sharpshooter is a Sniper mod that restores energy upon a headshot kill.",
        "wiki_link": "http://warframe.wikia.com/wiki/Sharpshooter",
        "drop": [
            {
                "name": "Arbitrations",
                "link": null
            }
        ]
    },
    "ru": {
        "item_name": "Sharpshooter",
        "description": "Sharpshooter is a Sniper mod that restores energy upon a headshot kill.",
        "wiki_link": "http://warframe.wikia.com/wiki/Sharpshooter",
        "drop": [
            {
                "name": "Arbitrations",
                "link": null
            }
        ]
    },
    "ko": {
        "item_name": "샤프슈터",
        "description": "Sharpshooter is a Sniper mod that restores energy upon a headshot kill.",
        "wiki_link": "http://warframe.wikia.com/wiki/Sharpshooter",
        "drop": [
            {
                "name": "Arbitrations",
                "link": null
            }
        ]
    },
    "rarity": "rare",
    "mod_max_rank": 10,
    "trading_tax": 8000
}