{
    "_id": "5eb5e49b04d55c04e80d6a81",
    "tags": [
        "mod",
        "shotguns",
        "prime",
        "legendary"
    ],
    "icon": "icons/en/primed_cleanse_infested.7607e9c16cfdfee6f0daad542044d20b.png",
    "thumb": "icons/en/thumbs/primed_cleanse_infested.7607e9c16cfdfee6f0daad542044d20b.128x128.png",
    "icon_format": "port",
    "url_name": "primed_cleanse_infested",
    "tradable": true,
    "en": {
        "item_name": "Primed Cleanse Infested",
        "description": "<p>Primed Cleanse Infested is the Primed version of the Cleanse Infested mod, which increases the damage of shotguns against Infested. The mod increases both the base damage and elemental damage of a weapon.</p>",
        "wiki_link": "https://warframe.fandom.com/wiki/Primed_Cleanse_Infested",
        "drop": [
            {
                "name": "Baro Ki'Teer",
                "link": null
            }
        ]
    },
    "ru": {
        "item_name": "Primed Cleanse Infested",
        "description": "<p>Primed Cleanse Infested is the Primed version of the Cleanse Infested mod, which increases the damage of shotguns against Infested. The mod increases both the base damage and elemental damage of a weapon.</p>",
        "wiki_link": "https://warframe.fandom.com/wiki/Primed_Cleanse_Infested",
        "drop": [
            {
                "name": "Baro Ki'Teer",
                "link": null
            }
        ]
    },
    "ko": {
        "item_name": "Primed Cleanse Infested",
        "description": "<p>Primed Cleanse Infested is the Primed version of the Cleanse Infested mod, which increases the damage of shotguns against Infested. The mod increases both the base damage and elemental damage of a weapon.</p>",
        "wiki_link": "https://warframe.fandom.com/wiki/Primed_Cleanse_Infested",
        "drop": [
            {
                "name": "Baro Ki'Teer",
                "link": null
            }
        ]
    },
    "rarity": "legendary",
    "mod_max_rank": 10,
    "trading_tax": 1000000
}