{
    "_id": "5c5ca81696e8d2003834fd83",
    "url_name": "miter",
    "group": "primary",
    "riven_type": "rifle",
    "icon": "icons/en/Miter.5e47b6ef364ad19e7df939a8b1c9f177.png",
    "thumb": "icons/en/thumbs/Miter.5e47b6ef364ad19e7df939a8b1c9f177.128x128.png",
    "icon_format": "land",
    "en": {
        "item_name": "Miter",
        "wiki_link": "http://warframe.wikia.com/wiki/Miter"
    },
    "ru": {
        "item_name": "Miter",
        "wiki_link": "http://warframe.wikia.com/wiki/Miter"
    },
    "ko": {
        "item_name": "마이터",
        "wiki_link": "http://warframe.wikia.com/wiki/Miter"
    }
}