{
    "_id": "5c5ca81696e8d2003834fd70",
    "url_name": "drakgoon",
    "group": "primary",
    "riven_type": "shotgun",
    "disposition": 1.4,
    "mastery_level": 5,
    "game_ref": {
        "uniq_name": "/Lotus/Weapons/Grineer/LongGuns/GrineerFlakCannon/FlakCannon"
    },
    "i18n": {
        "en": {
            "item_name": "Drakgoon",
            "wiki_link": "https://warframe.fandom.com/wiki/Drakgoon",
            "icon": "items/images/en/drakgoon.6b8dfef7ac875fa49f3418254b9a0d2b.png",
            "thumb": "items/images/en/thumbs/drakgoon.6b8dfef7ac875fa49f3418254b9a0d2b.128x128.png"
        },
        "ru": {
            "item_name": "Дракгун",
            "wiki_link": "https://warframe.fandom.com/ru/wiki/%D0%94%D1%80%D0%B0%D0%BA%D0%B3%D1%83%D0%BD",
            "icon": "items/images/en/drakgoon.6b8dfef7ac875fa49f3418254b9a0d2b.png",
            "thumb": "items/images/en/thumbs/drakgoon.6b8dfef7ac875fa49f3418254b9a0d2b.128x128.png"
        },
        "ko": {
            "item_name": "드락군",
            "wiki_link": "https://warframe.fandom.com/wiki/Drakgoon",
            "icon": "items/images/en/drakgoon.6b8dfef7ac875fa49f3418254b9a0d2b.png",
            "thumb": "items/images/en/thumbs/drakgoon.6b8dfef7ac875fa49f3418254b9a0d2b.128x128.png"
        },
        "de": {
            "item_name": "Drakgoon",
            "wiki_link": "https://warframe.fandom.com/de/wiki/Drakgoon",
            "icon": "items/images/en/drakgoon.6b8dfef7ac875fa49f3418254b9a0d2b.png",
            "thumb": "items/images/en/thumbs/drakgoon.6b8dfef7ac875fa49f3418254b9a0d2b.128x128.png"
        },
        "fr": {
            "item_name": "Drakgoon",
            "wiki_link": "https://warframe.fandom.com/fr/wiki/Drakgoon",
            "icon": "items/images/en/drakgoon.6b8dfef7ac875fa49f3418254b9a0d2b.png",
            "thumb": "items/images/en/thumbs/drakgoon.6b8dfef7ac875fa49f3418254b9a0d2b.128x128.png"
        },
        "pt": {
            "item_name": "Drakgoon",
            "wiki_link": "https://warframe.fandom.com/pt-br/wiki/Drakgoon",
            "icon": "items/images/en/drakgoon.6b8dfef7ac875fa49f3418254b9a0d2b.png",
            "thumb": "items/images/en/thumbs/drakgoon.6b8dfef7ac875fa49f3418254b9a0d2b.128x128.png"
        },
        "zh-hans": {
            "item_name": "龙骑兵",
            "wiki_link": "https://warframe.huijiwiki.com/wiki/Drakgoon",
            "icon": "items/images/en/drakgoon.6b8dfef7ac875fa49f3418254b9a0d2b.png",
            "thumb": "items/images/en/thumbs/drakgoon.6b8dfef7ac875fa49f3418254b9a0d2b.128x128.png"
        },
        "zh-hant": {
            "item_name": "龍騎兵",
            "wiki_link": "https://warframe.huijiwiki.com/wiki/Drakgoon",
            "icon": "items/images/en/drakgoon.6b8dfef7ac875fa49f3418254b9a0d2b.png",
            "thumb": "items/images/en/thumbs/drakgoon.6b8dfef7ac875fa49f3418254b9a0d2b.128x128.png"
        },
        "es": {
            "item_name": "Drakgoon",
            "wiki_link": "https://warframe.fandom.com/es/wiki/Drakgoon",
            "icon": "items/images/en/drakgoon.6b8dfef7ac875fa49f3418254b9a0d2b.png",
            "thumb": "items/images/en/thumbs/drakgoon.6b8dfef7ac875fa49f3418254b9a0d2b.128x128.png"
        },
        "it": {
            "item_name": "Drakgoon",
            "wiki_link": "https://warframe.fandom.com/it/wiki/Drakgoon",
            "icon": "items/images/en/drakgoon.6b8dfef7ac875fa49f3418254b9a0d2b.png",
            "thumb": "items/images/en/thumbs/drakgoon.6b8dfef7ac875fa49f3418254b9a0d2b.128x128.png"
        },
        "pl": {
            "item_name": "Drakgoon",
            "wiki_link": "https://warframe.fandom.com/pl/wiki/Drakgoon",
            "icon": "items/images/en/drakgoon.6b8dfef7ac875fa49f3418254b9a0d2b.png",
            "thumb": "items/images/en/thumbs/drakgoon.6b8dfef7ac875fa49f3418254b9a0d2b.128x128.png"
        },
        "uk": {
            "item_name": "Дракґун",
            "wiki_link": "https://warframe.fandom.com/wiki/Drakgoon",
            "icon": "items/images/en/drakgoon.6b8dfef7ac875fa49f3418254b9a0d2b.png",
            "thumb": "items/images/en/thumbs/drakgoon.6b8dfef7ac875fa49f3418254b9a0d2b.128x128.png"
        }
    }
}