{
    "_id": "5c5ca81696e8d2003834fdd1",
    "url_name": "marelok",
    "group": "secondary",
    "riven_type": "pistol",
    "icon": "icons/en/marelok.71aee4b391af97aa2376fe28d24fdf26.png",
    "thumb": "icons/en/thumbs/marelok.71aee4b391af97aa2376fe28d24fdf26.128x128.png",
    "icon_format": "land",
    "game_ref": {
        "uniq_name": "/Lotus/Weapons/Grineer/Pistols/GrineerLeverActionPistol/GLAPistol"
    },
    "en": {
        "item_name": "Marelok",
        "wiki_link": "https://warframe.fandom.com/wiki/Marelok"
    },
    "ru": {
        "item_name": "Мэрлок",
        "wiki_link": "https://warframe.fandom.com/ru/wiki/%D0%9C%D1%8D%D1%80%D0%BB%D0%BE%D0%BA"
    },
    "ko": {
        "item_name": "메어락",
        "wiki_link": "https://warframe.fandom.com/wiki/Marelok"
    },
    "de": {
        "item_name": "Marelok",
        "wiki_link": "https://warframe.fandom.com/de/wiki/Marelok"
    },
    "fr": {
        "item_name": "Marelok",
        "wiki_link": "https://warframe.fandom.com/fr/wiki/Marelok"
    },
    "pt": {
        "item_name": "Marelok",
        "wiki_link": "https://warframe.fandom.com/pt-br/wiki/Marelok"
    },
    "zh-hans": {
        "item_name": "玛瑞火枪",
        "wiki_link": "https://warframe.huijiwiki.com/wiki/Marelok"
    },
    "zh-hant": {
        "item_name": "瑪瑞火槍",
        "wiki_link": "https://warframe.huijiwiki.com/wiki/Marelok"
    },
    "es": {
        "item_name": "Marelok",
        "wiki_link": "https://warframe.fandom.com/es/wiki/Marelok"
    },
    "it": {
        "item_name": "Marelok",
        "wiki_link": "https://warframe.fandom.com/it/wiki/Marelok"
    },
    "pl": {
        "item_name": "Marelok",
        "wiki_link": "https://warframe.fandom.com/pl/wiki/Marelok"
    }
}