{
    "_id": "5c5ca81696e8d2003834fdd5",
    "url_name": "pyrana",
    "group": "secondary",
    "riven_type": "shotgun",
    "icon": "icons/en/pyrana.76c730b1909750965e34b2ca2e12da81.png",
    "thumb": "icons/en/thumbs/pyrana.76c730b1909750965e34b2ca2e12da81.128x128.png",
    "icon_format": "land",
    "en": {
        "item_name": "Pyrana",
        "wiki_link": "http://warframe.wikia.com/wiki/Pyrana"
    },
    "ru": {
        "item_name": "Pyrana",
        "wiki_link": "http://warframe.wikia.com/wiki/Pyrana"
    },
    "ko": {
        "item_name": "Pyrana",
        "wiki_link": "http://warframe.wikia.com/wiki/Pyrana"
    }
}