{
    "_id": "5cb04868fc2db2068006980c",
    "tags": [
        "mod",
        "revenant",
        "rare",
        "warframe"
    ],
    "icon": "icons/en/blinding_reave.bc2092c3e7d7e1a2e48e64bee12547cd.png",
    "thumb": "icons/en/thumbs/blinding_reave.bc2092c3e7d7e1a2e48e64bee12547cd.128x128.png",
    "icon_format": "port",
    "url_name": "blinding_reave",
    "tradable": true,
    "game_ref": {
        "uniq_name": "/Lotus/Powersuits/Revenant/RevenantAfflictionAugmentCard"
    },
    "en": {
        "item_name": "Blinding Reave",
        "description": "Reave Augment: Enemies hit are blinded by fog for 10s.",
        "wiki_link": "https://warframe.fandom.com/wiki/Blinding_Reave",
        "drop": []
    },
    "ru": {
        "item_name": "Ослепляющее Опустошение",
        "description": "Улучшение способности «Опустошение»: задетые враги будут ослеплены на 10 с.",
        "wiki_link": "https://warframe.fandom.com/ru/wiki/%D0%9E%D1%81%D0%BB%D0%B5%D0%BF%D0%BB%D1%8F%D1%8E%D1%89%D0%B5%D0%B5_%D0%9E%D0%BF%D1%83%D1%81%D1%82%D0%BE%D1%88%D0%B5%D0%BD%D0%B8%D0%B5",
        "icon": "icons/ru/blinding_reave.0d5bc8ceb7258d41a1b541a35682f276.png",
        "thumb": "icons/ru/thumbs/blinding_reave.0d5bc8ceb7258d41a1b541a35682f276.128x128.png",
        "drop": []
    },
    "ko": {
        "item_name": "블라인딩 리브",
        "description": "리브 개조: 피격된 적들이 안개에 의해 10초 동안 실명됩니다.",
        "wiki_link": "https://warframe.fandom.com/wiki/Blinding_Reave",
        "drop": []
    },
    "de": {
        "item_name": "Blendendes Schröpfen",
        "description": "Schröpfen Augment: Getroffenen Gegner werden für  10 s durch Nebel geblendet.",
        "wiki_link": "https://warframe.fandom.com/wiki/Blinding_Reave",
        "drop": []
    },
    "fr": {
        "item_name": "Pillage Aveuglant",
        "description": "Augmentation de Pillage: Les ennemis touchés sont aveuglés par un brouillard pendant 10s.",
        "wiki_link": "https://warframe.fandom.com/fr/wiki/Pillage_Ardent",
        "drop": []
    },
    "pt": {
        "item_name": "Blinding Reave",
        "description": "Ampliação Reave: Inimigos atingidos são cegados durante 10s.",
        "wiki_link": "https://warframe.fandom.com/pt-br/wiki/Blind_Rage",
        "drop": []
    },
    "zh-hans": {
        "item_name": "致盲掠夺",
        "description": "精华掠夺强化：被烟雾击中的敌人会被致盲 10 秒。",
        "wiki_link": "https://warframe.huijiwiki.com/wiki/Blinding_Reave",
        "drop": []
    },
    "zh-hant": {
        "item_name": "致盲掠奪",
        "description": "菁華掠奪強化：被煙霧擊中的敵人會被致盲 10 秒。",
        "wiki_link": "https://warframe.huijiwiki.com/wiki/Blinding_Reave",
        "drop": []
    },
    "es": {
        "item_name": "Drenaje Cegador",
        "description": "Aumento de Drenar: los enemigos golpeados son cegados por 10s.",
        "wiki_link": "https://warframe.fandom.com/es/wiki/Drenaje_cegador",
        "drop": []
    },
    "it": {
        "item_name": "Blinding Reave",
        "description": "Potenziamento Reave: I nemici colpiti sono accecati dalla nebbia per 10s.",
        "wiki_link": "https://warframe.fandom.com/wiki/Blinding_Reave",
        "drop": []
    },
    "pl": {
        "item_name": "Oślepiająca Zjawa",
        "description": "Modyfikacja Zjawy: Przeciwnicy są oślepieni przez 10s.",
        "wiki_link": "https://warframe.fandom.com/wiki/Blinding_Reave",
        "drop": []
    },
    "rarity": "rare",
    "max_rank": 3,
    "trading_tax": 8000
}