{
    "_id": "644b00227ec1900044b97727",
    "tags": [
        "legendary",
        "arcane_enhancement"
    ],
    "icon": "items/images/en/longbow_sharpshot.1edd43d82c3b61da2555a2ccb9ba9332.png",
    "thumb": "items/images/en/thumbs/longbow_sharpshot.1edd43d82c3b61da2555a2ccb9ba9332.128x128.png",
    "icon_format": "land",
    "url_name": "longbow_sharpshot",
    "tradable": true,
    "game_ref": {
        "uniq_name": "/Lotus/Upgrades/CosmeticEnhancers/Offensive/LongbowDamageOnHeadshot"
    },
    "en": {
        "item_name": "Longbow Sharpshot",
        "description": "On Headshot: Gain +300% damage on your next shot.",
        "wiki_link": null
    },
    "ru": {
        "item_name": "Меткая Стрела",
        "description": "При попадании в голову: Получите +300% к урону для последующего выстрела.",
        "wiki_link": null
    },
    "ko": {
        "item_name": "롱보우 샤프샷",
        "description": "헤드샷을 맞출 시: 다음 사격 시 +300%의 추가 피해를 얻습니다.",
        "wiki_link": null
    },
    "de": {
        "item_name": "Arkana: Langbogen Präzision",
        "description": "Bei Kopfschuss: Erhalte +300 % Schaden bei deinem nächsten Schuss.",
        "wiki_link": null
    },
    "fr": {
        "item_name": "Arc De Précision",
        "description": "Sur Tir à la tête: Gagnez +300% de Dégâts lors de votre prochain tir.",
        "wiki_link": null
    },
    "pt": {
        "item_name": "Artilheiro De Arco Longo",
        "description": "No Acerto de Precisão: Obtenha +300% de Dano no seu próximo disparo.",
        "wiki_link": null
    },
    "zh-hans": {
        "item_name": "弓箭·利矢",
        "description": "造成爆头后：下一次射击 +300% 伤害。",
        "wiki_link": null
    },
    "zh-hant": {
        "item_name": "長弓銳箭",
        "description": "爆頭時：下一次射擊 +300% 傷害。",
        "wiki_link": null
    },
    "es": {
        "item_name": "Precisión De Arco Largo",
        "description": "Al disparar a la cabeza: Gana +300 % de daño en tu próximo disparo.",
        "wiki_link": null
    },
    "it": {
        "item_name": "Longbow Sharpshot",
        "description": "Dopo un Colpo alla Testa: Ottieni +300% di danno al colpo successivo.",
        "wiki_link": null
    },
    "pl": {
        "item_name": "Celny Strzał Długiego Łuku",
        "description": "Po trafieniu w głowę: Zyskaj premię +300% obrażeń przy następnym strzale.",
        "wiki_link": null
    },
    "uk": {
        "item_name": "Стрілець Із Лука",
        "description": "У разі влучання в голову: Отримайте +300% до шкоди для наступного пострілу.",
        "wiki_link": null
    },
    "rarity": "legendary",
    "max_rank": 5,
    "trading_tax": 2100000.0
}