{
    "_id": "5dfea1441456970294aff38f",
    "tags": [
        "mod",
        "legendary",
        "melee"
    ],
    "icon": "items/images/en/primed_smite_corrupted.fd671126fd4051e8e3addc13ae56d1f0.png",
    "thumb": "items/images/en/thumbs/primed_smite_corrupted.fd671126fd4051e8e3addc13ae56d1f0.128x128.png",
    "icon_format": "port",
    "url_name": "primed_smite_corrupted",
    "tradable": true,
    "game_ref": {
        "uniq_name": "/Lotus/Upgrades/Mods/Melee/Expert/WeaponMeleeFactionDamageCorruptedExpert"
    },
    "i18n": {
        "en": {
            "item_name": "Primed Smite Corrupted",
            "description": "+55% Damage to Corrupted",
            "wiki_link": "https://warframe.fandom.com/wiki/Primed_Smite_Corrupted",
            "icon": "items/images/en/primed_smite_corrupted.fd671126fd4051e8e3addc13ae56d1f0.png",
            "thumb": "items/images/en/thumbs/primed_smite_corrupted.fd671126fd4051e8e3addc13ae56d1f0.128x128.png"
        },
        "ru": {
            "item_name": "Крушитель Прайм: Порабощённые",
            "description": "+55% урона Порабощённым",
            "wiki_link": "https://warframe.fandom.com/ru/wiki/%D0%9A%D1%80%D1%83%D1%88%D0%B8%D1%82%D0%B5%D0%BB%D1%8C_%D0%9F%D1%80%D0%B0%D0%B9%D0%BC:_%D0%9F%D0%BE%D1%80%D0%B0%D0%B1%D0%BE%D1%89%D0%B5%D0%BD%D0%BD%D1%8B%D0%B5"
        },
        "ko": {
            "item_name": "프라임드 스마이트 커럽티드",
            "description": "커럽티드에 대한 피해 +55%",
            "wiki_link": "https://warframe.fandom.com/wiki/Primed_Smite_Corrupted"
        },
        "de": {
            "item_name": "Primed Korrumpierte Bestrafen",
            "description": "+55 % Schaden an Korrumpierten",
            "wiki_link": "https://warframe.fandom.com/de/wiki/Korrumpierte_Verjagen"
        },
        "fr": {
            "item_name": "Châtie-Corrompus Accru",
            "description": "+55% de Dégâts aux Corrompus",
            "wiki_link": "https://warframe.fandom.com/fr/wiki/Ch%C3%A2tie-Corrompu_Accru"
        },
        "pt": {
            "item_name": "Primed Smite Corrupted",
            "description": "+55% de Dano em Corrompidos",
            "wiki_link": "https://warframe.fandom.com/wiki/Primed_Smite_Infested"
        },
        "zh-hans": {
            "item_name": "毁灭堕落者 Prime",
            "description": "+55% 对堕落者伤害",
            "wiki_link": "https://warframe.huijiwiki.com/wiki/Primed_Smite_Corrupted"
        },
        "zh-hant": {
            "item_name": "毀滅墮落者 Prime",
            "description": "+55% 對墮落者傷害",
            "wiki_link": "https://warframe.huijiwiki.com/wiki/Primed_Smite_Corrupted"
        },
        "es": {
            "item_name": "Castiga Corruptos Prime",
            "description": "+55% de daño contra Corruptos",
            "wiki_link": "https://warframe.fandom.com/es/wiki/Castiga_Corruptos"
        },
        "it": {
            "item_name": "Primed Smite Corrupted",
            "description": "+55% Danno su Corrupted",
            "wiki_link": "https://warframe.fandom.com/wiki/Primed_Smite_Infested"
        },
        "pl": {
            "item_name": "Rozpruwacz Skażonych Prime",
            "description": "+55% Obrażeń zadawanych Skażonym",
            "wiki_link": "https://warframe.fandom.com/wiki/Primed_Smite_Infested"
        },
        "uk": {
            "item_name": "Праймоване Вирізання Уярмлених",
            "description": "+55% до завдаваної шкоди уярмленим",
            "wiki_link": "https://warframe.fandom.com/wiki/Primed_Smite_Corrupted"
        }
    },
    "rarity": "legendary",
    "max_rank": 10,
    "trading_tax": 1000000
}