{
    "_id": "59eba86952f90ed715e14155",
    "tags": [
        "gems",
        "gem"
    ],
    "icon": "icons/en/Tear_Azurite.e2f857f217db500bb173a7a4e518958e.png",
    "thumb": "icons/en/thumbs/Tear_Azurite.e2f857f217db500bb173a7a4e518958e.128x128.png",
    "icon_format": "port",
    "url_name": "tear_azurite",
    "tradable": true,
    "game_ref": {
        "uniq_name": "/Lotus/Types/Items/Gems/Eidolon/CommonGemACutAItem"
    },
    "en": {
        "item_name": "Tear Azurite",
        "description": "Polished and cut to perfection.\nBlueprint sold by Old Man Suumbaat in Cetus, Earth.",
        "wiki_link": "https://warframe.fandom.com/wiki/Tear_Azurite",
        "drop": []
    },
    "ru": {
        "item_name": "Азурит-слеза",
        "description": "Отполированный и ограненный до совершенства.\nЧертёж можно купить у старика Суумбаата в Цетусе на Земле.",
        "wiki_link": "https://warframe.fandom.com/ru/wiki/%D0%90%D0%B7%D1%83%D1%80%D0%B8%D1%82-%D1%81%D0%BB%D0%B5%D0%B7%D0%B0",
        "drop": []
    },
    "ko": {
        "item_name": "티어 아주라이트",
        "description": "완벽하게 갈고 광을 낸 보석입니다.\n지구의 시터스에 있는 노인 숨바트에게서 설계도를 구매할 수 있습니다.",
        "wiki_link": "https://warframe.fandom.com/wiki/Tear_Azurite",
        "drop": []
    },
    "de": {
        "item_name": "Azurit-träne",
        "description": "Poliert und perfekt geschnitten.\nFundort: Blaupause erhältlich von Old Man Suumbaat in Cetus, Erde.",
        "wiki_link": "https://warframe.fandom.com/de/wiki/Azurite-Tr%C3%A4ne",
        "drop": []
    },
    "fr": {
        "item_name": "Larme D'azurite",
        "description": "Polie et taillée à la perfection.\nSchéma vendu par le Vieux Suumbat dans Cetus, Terre.",
        "wiki_link": "https://warframe.fandom.com/fr/wiki/Larme_d%27Azurite",
        "drop": []
    },
    "pt": {
        "item_name": "Azurite Gotejada",
        "description": "Polida e talhada à perfeição.\nSeu Diagrama pode ser obtido junto ao Ancião Suumbat, em Cetus, na Terra.",
        "wiki_link": "http://warframe.wikia.com/wiki/Tear_Azurite",
        "drop": []
    },
    "zh-hans": {
        "item_name": "泪滴形石青",
        "description": "切割打磨至完美无瑕。\n来源：地球上希图斯的老者 Suumbaat 出售的蓝图。",
        "wiki_link": "https://warframe.huijiwiki.com/wiki/Tear_Azurite",
        "drop": []
    },
    "zh-hant": {
        "item_name": "淚滴形藍銅礦石",
        "description": "經切割打磨後至完美狀態。\n來源：老者 Suumbaat 出售的藍圖（希圖斯，地球）。",
        "wiki_link": "https://warframe.huijiwiki.com/wiki/Tear_Azurite",
        "drop": []
    },
    "es": {
        "item_name": "Azurita Cortada",
        "description": "Pulida y cortada a la perfección.\nEl plano lo vende el anciano Suumbat en Cetus, Tierra.",
        "wiki_link": "https://warframe.fandom.com/es/wiki/Azurita_cortada",
        "drop": []
    },
    "it": {
        "item_name": "Azzurrite A Goccia",
        "description": "Lucidato e tagliato alla perfezione.\nLo schema è acquistabile dal Vecchietto Suumbaat su Cetus (Terra).",
        "wiki_link": "http://warframe.wikia.com/wiki/Tear_Azurite",
        "drop": []
    },
    "pl": {
        "item_name": "Łza Azurytu",
        "description": "Przycięty i oszlifowany do perfekcji.\nSchemat do kupienia u Starca Suumbaat na Cetus, Ziemia.",
        "wiki_link": "https://warframe.fandom.com/pl/wiki/%C5%81za_Azurytu",
        "drop": []
    },
    "trading_tax": 2000
}